sphinx_scrapy/__init__.py
sphinx_scrapy-0.6.1.dist-info/METADATA
sphinx_scrapy-0.6.1.dist-info/WHEEL
sphinx_scrapy-0.6.1.dist-info/licenses/LICENSE
sphinx_scrapy-0.6.1.dist-info/RECORD
