Metadata-Version: 2.4
Name: sphinx-scrapy
Version: 0.6.1
Summary: Sphinx extension for documentation in the Scrapy ecosystem
Project-URL: Source, https://github.com/scrapy/sphinx-scrapy
Project-URL: Tracker, https://github.com/scrapy/sphinx-scrapy/issues
Project-URL: Release notes, https://github.com/scrapy/sphinx-scrapy/blob/main/CHANGES.rst
Author-email: Scrapy developers <opensource@zyte.com>
Maintainer-email: Scrapy developers <opensource@zyte.com>
License-Expression: BSD-3-Clause
License-File: LICENSE
Classifier: Development Status :: 4 - Beta
Classifier: Framework :: Scrapy
Classifier: Intended Audience :: Developers
Classifier: Operating System :: OS Independent
Classifier: Programming Language :: Python
Classifier: Programming Language :: Python :: 3
Classifier: Programming Language :: Python :: 3.8
Classifier: Programming Language :: Python :: 3.9
Classifier: Programming Language :: Python :: 3.10
Classifier: Programming Language :: Python :: 3.11
Classifier: Programming Language :: Python :: 3.12
Classifier: Programming Language :: Python :: 3.13
Classifier: Topic :: Internet :: WWW/HTTP
Classifier: Topic :: Software Development :: Libraries :: Application Frameworks
Classifier: Topic :: Software Development :: Libraries :: Python Modules
Requires-Python: >=3.8
Requires-Dist: sphinx
